[
	// dirt age
	{
		"columnNumber": 0,
		"era": "Dirt Age",
		"techCost": 2,
		"buildingCost": 40,
		"wonderCost": 180,
		"techs": [
			{
				"name": "digging",
				"row": 2,
				"quote": "'diggy diggy mole hole' - mole",
				"uniques": ["Starting tech"],
				"civilopediaText": [
					{
						"text": "The starting technology."
					}
				]
			}
		]
  }
  {
		"columnNumber": 1,
		"era": "Dirt Age",
		"techCost": 2,
		"buildingCost": 40,
		"wonderCost": 180,
		"techs": [
			{
				"name": "Tribalism",
				"row": 1,
				"quote": "'i just woke up in a new bugatti' - some guy",
        			"prerequisites": ["digging"],
				"uniques": [""],
				"civilopediaText": [
					{
						"text": "i just woke up in a new bugatti"
					}
				]
			},
      			{
				"name": "Gathering",
				"row": 2,
				"quote": "'i just woke up in a new bugatti' - some guy",
        			"prerequisites": ["digging"],
				"uniques": ["[+1 Production] [in all cities]"],
				"civilopediaText": [
					{
						"text": "i just woke up in a new bugatti"
					}
				]
			},
      			{
				"name": "Sharp Sticks",
				"row": 3,
				"quote": "'i just woke up in a new bugatti' - some guy",
        			"prerequisites": ["digging"],
				"uniques": ["[+10]% Strength <for [All] units> <when attacking>", "[+10]% Strength <for [All] units> <when defending>"],
				"civilopediaText": [
					{
						"text": "i just woke up in a new bugatti"
					}
				]
			},
      			{
				"name": "Pottery",
				"row": 4,
				"quote": "'i just woke up in a new bugatti' - some guy",
        			"prerequisites": ["digging"],
				"uniques": ["[+5 Faith] [in all cities]"],
				"civilopediaText": [
					{
						"text": "i just woke up in a new bugatti"
					}
				]
			}
		]
  }
	// stone age
  {
		"columnNumber": 2,
		"era": "Stone Age",
		"techCost": 5,
		"buildingCost": 40,
		"wonderCost": 180,
		"techs": [
			{
				"name": "Stone Tools",
				"row": 2,
				"quote": "'i just woke up in a new bugatti' - some guy",
				"prerequisites": ["Tribalism", "Gathering", "Sharp Sticks", "Pottery"],
				"uniques": [""],
				"civilopediaText": [
					{
						"text": "i just woke up in a new bugatti"
					}
				]
			}
		]
  }
]
